{
  "generated_at": "2026-05-03T21:33:47.531690+09:00",
  "n_active": 21,
  "total_ev_per_day": 41095.294871794875,
  "compressed_real": 19438.11794871795,
  "compressed_weighted": 28256.84266666667,
  "target": 29700,
  "rows": [
    {
      "symbol": "6752.T",
      "strategy": "MacdRci",
      "expected_value": 8348.0,
      "share_pct": 20.31,
      "lot_multiplier": 3.0,
      "base_mult": 3.0,
      "source": "60d_actual",
      "q2_cap_applied": false,
      "actual_60d": 8348.128205128205,
      "wf_oos": 3072.2
    },
    {
      "symbol": "6954.T",
      "strategy": "MacdRci",
      "expected_value": 4375.0,
      "share_pct": 10.65,
      "lot_multiplier": 2.24,
      "base_mult": 2.24,
      "source": "60d_actual",
      "q2_cap_applied": false,
      "actual_60d": 4375.0,
      "wf_oos": 4267.2
    },
    {
      "symbol": "9984.T",
      "strategy": "EnhancedMacdRci",
      "expected_value": 3661.0,
      "share_pct": 8.91,
      "lot_multiplier": 1.87,
      "base_mult": 1.87,
      "source": "60d_actual",
      "q2_cap_applied": false,
      "actual_60d": 3661.0,
      "wf_oos": 12168.1
    },
    {
      "symbol": "6723.T",
      "strategy": "MacdRci",
      "expected_value": 2154.0,
      "share_pct": 5.24,
      "lot_multiplier": 1.1,
      "base_mult": 1.1,
      "source": "60d_actual",
      "q2_cap_applied": false,
      "actual_60d": 2154.4358974358975,
      "wf_oos": 1471.4
    },
    {
      "symbol": "6752.T",
      "strategy": "EnhancedMacdRci",
      "expected_value": 2034.0,
      "share_pct": 4.95,
      "lot_multiplier": 1.04,
      "base_mult": 1.04,
      "source": "60d_actual",
      "q2_cap_applied": false,
      "actual_60d": 2034.0,
      "wf_oos": 2034.0
    },
    {
      "symbol": "1605.T",
      "strategy": "MicroScalp",
      "expected_value": 2289.0,
      "share_pct": 5.57,
      "lot_multiplier": 1.0,
      "base_mult": 1.17,
      "source": "oos_daily",
      "q2_cap_applied": true,
      "actual_60d": null,
      "wf_oos": 2289.0
    },
    {
      "symbol": "6501.T",
      "strategy": "MicroScalp",
      "expected_value": 2322.0,
      "share_pct": 5.65,
      "lot_multiplier": 1.0,
      "base_mult": 1.19,
      "source": "oos_daily",
      "q2_cap_applied": true,
      "actual_60d": null,
      "wf_oos": 2322.0
    },
    {
      "symbol": "8411.T",
      "strategy": "MacdRci",
      "expected_value": 4746.0,
      "share_pct": 11.55,
      "lot_multiplier": 1.0,
      "base_mult": 2.43,
      "source": "oos_daily",
      "q2_cap_applied": true,
      "actual_60d": null,
      "wf_oos": 4746.5
    },
    {
      "symbol": "8058.T",
      "strategy": "MacdRci",
      "expected_value": 1792.0,
      "share_pct": 4.36,
      "lot_multiplier": 0.92,
      "base_mult": 0.92,
      "source": "60d_actual",
      "q2_cap_applied": false,
      "actual_60d": 1791.8974358974358,
      "wf_oos": 446.7
    },
    {
      "symbol": "9432.T",
      "strategy": "MacdRci",
      "expected_value": 1771.0,
      "share_pct": 4.31,
      "lot_multiplier": 0.9,
      "base_mult": 0.9,
      "source": "60d_actual",
      "q2_cap_applied": false,
      "actual_60d": 1771.0,
      "wf_oos": 187.1
    },
    {
      "symbol": "9984.T",
      "strategy": "MacdRci",
      "expected_value": 1534.0,
      "share_pct": 3.73,
      "lot_multiplier": 0.78,
      "base_mult": 0.78,
      "source": "60d_actual",
      "q2_cap_applied": false,
      "actual_60d": 1533.7948717948718,
      "wf_oos": 8936.9
    },
    {
      "symbol": "9107.T",
      "strategy": "MacdRci",
      "expected_value": 1162.0,
      "share_pct": 2.83,
      "lot_multiplier": 0.59,
      "base_mult": 0.59,
      "source": "60d_actual",
      "q2_cap_applied": false,
      "actual_60d": 1161.974358974359,
      "wf_oos": 1953.7
    },
    {
      "symbol": "9433.T",
      "strategy": "MicroScalp",
      "expected_value": 1042.0,
      "share_pct": 2.54,
      "lot_multiplier": 0.53,
      "base_mult": 0.53,
      "source": "oos_daily",
      "q2_cap_applied": false,
      "actual_60d": null,
      "wf_oos": 1042.0
    },
    {
      "symbol": "9468.T",
      "strategy": "MacdRci",
      "expected_value": 483.0,
      "share_pct": 1.17,
      "lot_multiplier": 0.5,
      "base_mult": 0.5,
      "source": "60d_actual",
      "q2_cap_applied": false,
      "actual_60d": 482.56410256410254,
      "wf_oos": 1597.1
    },
    {
      "symbol": "6723.T",
      "strategy": "Breakout",
      "expected_value": 133.0,
      "share_pct": 0.32,
      "lot_multiplier": 0.5,
      "base_mult": 0.5,
      "source": "60d_actual",
      "q2_cap_applied": false,
      "actual_60d": 133.0,
      "wf_oos": 1632.0
    },
    {
      "symbol": "8136.T",
      "strategy": "Pullback",
      "expected_value": 905.0,
      "share_pct": 2.2,
      "lot_multiplier": 0.5,
      "base_mult": 0.5,
      "source": "60d_actual",
      "q2_cap_applied": false,
      "actual_60d": 905.0,
      "wf_oos": 2456.0
    },
    {
      "symbol": "9468.T",
      "strategy": "MicroScalp",
      "expected_value": 478.0,
      "share_pct": 1.16,
      "lot_multiplier": 0.5,
      "base_mult": 0.5,
      "source": "oos_daily",
      "q2_cap_applied": false,
      "actual_60d": null,
      "wf_oos": 478.0
    },
    {
      "symbol": "9433.T",
      "strategy": "BbShort",
      "expected_value": 512.0,
      "share_pct": 1.25,
      "lot_multiplier": 0.5,
      "base_mult": 0.5,
      "source": "60d_actual",
      "q2_cap_applied": false,
      "actual_60d": 512.0,
      "wf_oos": 512.0
    },
    {
      "symbol": "3103.T",
      "strategy": "BbShort",
      "expected_value": 472.0,
      "share_pct": 1.15,
      "lot_multiplier": 0.5,
      "base_mult": 0.5,
      "source": "60d_actual",
      "q2_cap_applied": false,
      "actual_60d": 472.0,
      "wf_oos": 472.0
    },
    {
      "symbol": "6501.T",
      "strategy": "BbShort",
      "expected_value": 351.0,
      "share_pct": 0.85,
      "lot_multiplier": 0.5,
      "base_mult": 0.5,
      "source": "60d_actual",
      "q2_cap_applied": false,
      "actual_60d": 351.0,
      "wf_oos": 351.0
    },
    {
      "symbol": "9468.T",
      "strategy": "Pullback",
      "expected_value": 531.0,
      "share_pct": 1.29,
      "lot_multiplier": 0.5,
      "base_mult": 0.5,
      "source": "60d_actual",
      "q2_cap_applied": false,
      "actual_60d": 531.0,
      "wf_oos": 295.0
    }
  ]
}